borsaAPI/__init__.py
borsaAPI/borsaAPI.py
borsaAPI-0.1.1.3.dist-info/METADATA
borsaAPI-0.1.1.3.dist-info/WHEEL
borsaAPI-0.1.1.3.dist-info/top_level.txt
borsaAPI-0.1.1.3.dist-info/RECORD
