Metadata-Version: 2.1
Name: borsaAPI
Version: 0.1.1.3
Summary: Python kütüphanesi ile hisse verisi çekme API'si
Home-page: UNKNOWN
Author: Bora Kaya
Author-email: borakaya8@gmail.com
License: UNKNOWN
Platform: UNKNOWN
Classifier: Programming Language :: Python :: 3
Classifier: License :: OSI Approved :: MIT License
Classifier: Operating System :: OS Independent
Requires-Python: >=3.6
Requires-Dist: requests
Requires-Dist: pandas
